maia2-stubs/__init__.py
maia2-stubs/__init__.pyi
maia2-stubs/dataset.pyi
maia2-stubs/inference.pyi
maia2-stubs/main.pyi
maia2-stubs/model.pyi
maia2-stubs/py.typed
maia2-stubs/train.pyi
maia2-stubs/utils.pyi
maia2_stubs-0.1.1.dist-info/licenses/LICENSE
maia2_stubs-0.1.1.dist-info/WHEEL
maia2_stubs-0.1.1.dist-info/METADATA
maia2_stubs-0.1.1.dist-info/RECORD
