Metadata-Version: 2.4
Name: maia2-stubs
Version: 0.1.1
Summary: Typing stubs for the maia2 package
Author-email: uspectacle <uspectacle@gmail.com>
Requires-Python: >=3.8
License-File: LICENSE
Requires-Dist: mypy ; extra == "test"
Project-URL: Home, https://github.com/Uspectacle/maia2-stubs
Project-URL: Source, https://github.com/CSSLab/maia2
Provides-Extra: test
